[
    {
        "Team": "TOR",
		"Player": "Alejandro Kirk",
        "Age": "26",
        "Pos": "C",
        "WAR": "1.7",
        "G": "88",
        "PA": "346",
        "AB": "312",
        "R": "27",
        "H": "95",
        "[2B]": "13",
        "[3B]": "0",
        "HR": "7",
        "RBI": "47",
        "SB": "0",
        "CS": "0",
        "BB": "29",
        "SO": "34",
        "BA": ".304",
        "OBP": ".361",
        "SLG": ".413",
        "OPS": ".775",
        "[OPS+]": "115",
        "rOBA": ".339",
        "[Rbat+]": "114",
        "TB": "129",
        "GIDP": "8",
        "HBP": "1",
        "SH": "0",
        "SF": "4",
        "IBB": "2"
    },
    {
        "Team": "TOR",
		"Player": "Vladimir Guerrero Jr.",
        "Age": "26",
        "Pos": "1B",
        "WAR": "3.5",
        "G": "105",
        "PA": "465",
        "AB": "394",
        "R": "71",
        "H": "116",
        "[2B]": "23",
        "[3B]": "0",
        "HR": "15",
        "RBI": "56",
        "SB": "5",
        "CS": "2",
        "BB": "63",
        "SO": "65",
        "BA": ".294",
        "OBP": ".398",
        "SLG": ".467",
        "OPS": ".865",
        "[OPS+]": "139",
        "rOBA": ".375",
        "[Rbat+]": "141",
        "TB": "184",
        "GIDP": "9",
        "HBP": "6",
        "SH": "0",
        "SF": "2",
        "IBB": "7"
    },
    {
        "Team": "TOR",
		"Player": "Andrés Giménez",
        "Age": "26",
        "Pos": "2B",
        "WAR": "1.1",
        "G": "61",
        "PA": "238",
        "AB": "211",
        "R": "26",
        "H": "46",
        "[2B]": "7",
        "[3B]": "0",
        "HR": "5",
        "RBI": "23",
        "SB": "10",
        "CS": "1",
        "BB": "16",
        "SO": "39",
        "BA": ".218",
        "OBP": ".300",
        "SLG": ".322",
        "OPS": ".622",
        "[OPS+]": "73",
        "rOBA": ".295",
        "[Rbat+]": "76",
        "TB": "68",
        "GIDP": "3",
        "HBP": "9",
        "SH": "1",
        "SF": "1",
        "IBB": "0"
    },
    {
        "Team": "TOR",
		"Player": "Bo Bichette",
        "Age": "27",
        "Pos": "SS",
        "WAR": "2.5",
        "G": "104",
        "PA": "470",
        "AB": "441",
        "R": "50",
        "H": "130",
        "[2B]": "32",
        "[3B]": "1",
        "HR": "13",
        "RBI": "65",
        "SB": "4",
        "CS": "3",
        "BB": "24",
        "SO": "72",
        "BA": ".295",
        "OBP": ".334",
        "SLG": ".460",
        "OPS": ".794",
        "[OPS+]": "118",
        "rOBA": ".345",
        "[Rbat+]": "119",
        "TB": "203",
        "GIDP": "10",
        "HBP": "3",
        "SH": "0",
        "SF": "2",
        "IBB": "2"
    },
    {
        "Team": "TOR",
		"Player": "Ernie Clement",
        "Age": "29",
        "Pos": "3B",
        "WAR": "2.2",
        "G": "105",
        "PA": "391",
        "AB": "360",
        "R": "50",
        "H": "100",
        "[2B]": "20",
        "[3B]": "1",
        "HR": "5",
        "RBI": "31",
        "SB": "3",
        "CS": "3",
        "BB": "20",
        "SO": "40",
        "BA": ".278",
        "OBP": ".313",
        "SLG": ".381",
        "OPS": ".694",
        "[OPS+]": "92",
        "rOBA": ".298",
        "[Rbat+]": "86",
        "TB": "137",
        "GIDP": "9",
        "HBP": "1",
        "SH": "5",
        "SF": "5",
        "IBB": "1"
    },
    {
        "Team": "TOR",
		"Player": "Alan Roden",
        "Age": "25",
        "Pos": "LF",
        "WAR": "-0.1",
        "G": "43",
        "PA": "113",
        "AB": "98",
        "R": "12",
        "H": "20",
        "[2B]": "5",
        "[3B]": "1",
        "HR": "1",
        "RBI": "8",
        "SB": "0",
        "CS": "1",
        "BB": "8",
        "SO": "24",
        "BA": ".204",
        "OBP": ".283",
        "SLG": ".306",
        "OPS": ".589",
        "[OPS+]": "64",
        "rOBA": ".257",
        "[Rbat+]": "57",
        "TB": "30",
        "GIDP": "0",
        "HBP": "4",
        "SH": "0",
        "SF": "3",
        "IBB": "0"
    },
    {
        "Team": "TOR",
		"Player": "Myles Straw",
        "Age": "30",
        "Pos": "CF",
        "WAR": "1.7",
        "G": "88",
        "PA": "207",
        "AB": "187",
        "R": "32",
        "H": "46",
        "[2B]": "10",
        "[3B]": "0",
        "HR": "1",
        "RBI": "17",
        "SB": "7",
        "CS": "1",
        "BB": "12",
        "SO": "31",
        "BA": ".246",
        "OBP": ".294",
        "SLG": ".316",
        "OPS": ".609",
        "[OPS+]": "69",
        "rOBA": ".286",
        "[Rbat+]": "70",
        "TB": "59",
        "GIDP": "5",
        "HBP": "1",
        "SH": "6",
        "SF": "1",
        "IBB": "0"
    },
    {
        "Team": "TOR",
		"Player": "Addison Barger",
        "Age": "25",
        "Pos": "RF",
        "WAR": "1.5",
        "G": "83",
        "PA": "311",
        "AB": "288",
        "R": "44",
        "H": "76",
        "[2B]": "24",
        "[3B]": "1",
        "HR": "14",
        "RBI": "48",
        "SB": "3",
        "CS": "1",
        "BB": "21",
        "SO": "77",
        "BA": ".264",
        "OBP": ".316",
        "SLG": ".500",
        "OPS": ".816",
        "[OPS+]": "122",
        "rOBA": ".342",
        "[Rbat+]": "116",
        "TB": "144",
        "GIDP": "3",
        "HBP": "1",
        "SH": "0",
        "SF": "0",
        "IBB": "4"
    },
    {
        "Team": "TOR",
		"Player": "George Springer",
        "Age": "35",
        "Pos": "DH",
        "WAR": "2.3",
        "G": "101",
        "PA": "408",
        "AB": "344",
        "R": "66",
        "H": "100",
        "[2B]": "18",
        "[3B]": "1",
        "HR": "18",
        "RBI": "57",
        "SB": "12",
        "CS": "0",
        "BB": "51",
        "SO": "76",
        "BA": ".291",
        "OBP": ".383",
        "SLG": ".506",
        "OPS": ".889",
        "[OPS+]": "144",
        "rOBA": ".390",
        "[Rbat+]": "147",
        "TB": "174",
        "GIDP": "10",
        "HBP": "3",
        "SH": "0",
        "SF": "4",
        "IBB": "1"
    },
    {
        "Team": "TOR",
		"Player": "Nathan Lukes",
        "Age": "30",
        "Pos": "OF",
        "WAR": "1.4",
        "G": "81",
        "PA": "257",
        "AB": "220",
        "R": "34",
        "H": "58",
        "[2B]": "8",
        "[3B]": "0",
        "HR": "8",
        "RBI": "38",
        "SB": "1",
        "CS": "2",
        "BB": "28",
        "SO": "33",
        "BA": ".264",
        "OBP": ".351",
        "SLG": ".409",
        "OPS": ".760",
        "[OPS+]": "110",
        "rOBA": ".332",
        "[Rbat+]": "112",
        "TB": "90",
        "GIDP": "8",
        "HBP": "2",
        "SH": "6",
        "SF": "1",
        "IBB": "2"
    },
    {
        "Team": "TOR",
		"Player": "Anthony Santander",
        "Age": "30",
        "Pos": "DH",
        "WAR": "-0.9",
        "G": "50",
        "PA": "209",
        "AB": "184",
        "R": "14",
        "H": "33",
        "[2B]": "5",
        "[3B]": "0",
        "HR": "6",
        "RBI": "18",
        "SB": "0",
        "CS": "0",
        "BB": "24",
        "SO": "55",
        "BA": ".179",
        "OBP": ".273",
        "SLG": ".304",
        "OPS": ".577",
        "[OPS+]": "60",
        "rOBA": ".258",
        "[Rbat+]": "55",
        "TB": "56",
        "GIDP": "6",
        "HBP": "0",
        "SH": "0",
        "SF": "1",
        "IBB": "1"
    },
    {
        "Team": "TOR",
		"Player": "Will Wagner",
        "Age": "26",
        "Pos": "CI",
        "WAR": "-0.2",
        "G": "37",
        "PA": "122",
        "AB": "106",
        "R": "13",
        "H": "25",
        "[2B]": "7",
        "[3B]": "0",
        "HR": "0",
        "RBI": "7",
        "SB": "1",
        "CS": "0",
        "BB": "13",
        "SO": "24",
        "BA": ".236",
        "OBP": ".331",
        "SLG": ".302",
        "OPS": ".632",
        "[OPS+]": "78",
        "rOBA": ".312",
        "[Rbat+]": "93",
        "TB": "32",
        "GIDP": "1",
        "HBP": "2",
        "SH": "1",
        "SF": "0",
        "IBB": "0"
    },
    {
        "Team": "TOR",
		"Player": "Tyler Heineman",
        "Age": "34",
        "Pos": "C",
        "WAR": "1.6",
        "G": "39",
        "PA": "114",
        "AB": "98",
        "R": "19",
        "H": "32",
        "[2B]": "7",
        "[3B]": "1",
        "HR": "3",
        "RBI": "16",
        "SB": "2",
        "CS": "0",
        "BB": "7",
        "SO": "21",
        "BA": ".327",
        "OBP": ".387",
        "SLG": ".510",
        "OPS": ".898",
        "[OPS+]": "147",
        "rOBA": ".383",
        "[Rbat+]": "144",
        "TB": "50",
        "GIDP": "1",
        "HBP": "4",
        "SH": "3",
        "SF": "2",
        "IBB": "0"
    },
    {
        "Team": "TOR",
		"Player": "Jonatan Clase",
        "Age": "23",
        "Pos": "LF",
        "WAR": "-0.1",
        "G": "34",
        "PA": "112",
        "AB": "100",
        "R": "10",
        "H": "21",
        "[2B]": "3",
        "[3B]": "0",
        "HR": "2",
        "RBI": "9",
        "SB": "3",
        "CS": "1",
        "BB": "10",
        "SO": "28",
        "BA": ".210",
        "OBP": ".288",
        "SLG": ".300",
        "OPS": ".588",
        "[OPS+]": "64",
        "rOBA": ".265",
        "[Rbat+]": "58",
        "TB": "30",
        "GIDP": "1",
        "HBP": "1",
        "SH": "1",
        "SF": "0",
        "IBB": "0"
    },
    {
        "Team": "TOR",
		"Player": "Davis Schneider",
        "Age": "26",
        "Pos": "LF",
        "WAR": "0.3",
        "G": "42",
        "PA": "109",
        "AB": "88",
        "R": "16",
        "H": "18",
        "[2B]": "3",
        "[3B]": "0",
        "HR": "5",
        "RBI": "12",
        "SB": "0",
        "CS": "1",
        "BB": "19",
        "SO": "31",
        "BA": ".205",
        "OBP": ".358",
        "SLG": ".409",
        "OPS": ".767",
        "[OPS+]": "113",
        "rOBA": ".343",
        "[Rbat+]": "120",
        "TB": "36",
        "GIDP": "3",
        "HBP": "2",
        "SH": "0",
        "SF": "0",
        "IBB": "0"
    },
    {
        "Team": "TOR",
		"Player": "Daulton Varsho",
        "Age": "28",
        "Pos": "CF",
        "WAR": "0.8",
        "G": "24",
        "PA": "100",
        "AB": "92",
        "R": "14",
        "H": "19",
        "[2B]": "5",
        "[3B]": "1",
        "HR": "8",
        "RBI": "20",
        "SB": "1",
        "CS": "0",
        "BB": "5",
        "SO": "31",
        "BA": ".207",
        "OBP": ".240",
        "SLG": ".543",
        "OPS": ".783",
        "[OPS+]": "108",
        "rOBA": ".316",
        "[Rbat+]": "96",
        "TB": "50",
        "GIDP": "0",
        "HBP": "0",
        "SH": "0",
        "SF": "3",
        "IBB": "1"
    },
    {
        "Team": "TOR",
		"Player": "Joey Loperfido",
        "Age": "26",
        "Pos": "OF",
        "WAR": "0.3",
        "G": "16",
        "PA": "48",
        "AB": "44",
        "R": "4",
        "H": "15",
        "[2B]": "1",
        "[3B]": "0",
        "HR": "2",
        "RBI": "7",
        "SB": "1",
        "CS": "0",
        "BB": "3",
        "SO": "11",
        "BA": ".341",
        "OBP": ".396",
        "SLG": ".500",
        "OPS": ".896",
        "[OPS+]": "147",
        "rOBA": ".413",
        "[Rbat+]": "165",
        "TB": "22",
        "GIDP": "0",
        "HBP": "1",
        "SH": "0",
        "SF": "0",
        "IBB": "0"
    },
    {
        "Team": "TOR",
		"Player": "Leo Jiménez",
        "Age": "24",
        "Pos": "MI",
        "WAR": "-0.3",
        "G": "15",
        "PA": "31",
        "AB": "28",
        "R": "2",
        "H": "2",
        "[2B]": "0",
        "[3B]": "0",
        "HR": "1",
        "RBI": "1",
        "SB": "0",
        "CS": "0",
        "BB": "2",
        "SO": "8",
        "BA": ".071",
        "OBP": ".133",
        "SLG": ".179",
        "OPS": ".312",
        "[OPS+]": "-14",
        "rOBA": ".173",
        "[Rbat+]": "-11",
        "TB": "5",
        "GIDP": "1",
        "HBP": "0",
        "SH": "1",
        "SF": "0",
        "IBB": "0"
    },
    {
        "Team": "TOR",
		"Player": "Michael Stefanic",
        "Age": "29",
        "Pos": "2B",
        "WAR": "0.0",
        "G": "9",
        "PA": "25",
        "AB": "22",
        "R": "1",
        "H": "4",
        "[2B]": "0",
        "[3B]": "0",
        "HR": "0",
        "RBI": "0",
        "SB": "0",
        "CS": "0",
        "BB": "3",
        "SO": "3",
        "BA": ".182",
        "OBP": ".280",
        "SLG": ".182",
        "OPS": ".462",
        "[OPS+]": "33",
        "rOBA": ".221",
        "[Rbat+]": "28",
        "TB": "4",
        "GIDP": "0",
        "HBP": "0",
        "SH": "0",
        "SF": "0",
        "IBB": "0"
    },
    {
        "Team": "TOR",
		"Player": "Will Robertson",
        "Age": "27",
        "Pos": "OF",
        "WAR": "-0.2",
        "G": "3",
        "PA": "12",
        "AB": "10",
        "R": "0",
        "H": "1",
        "[2B]": "0",
        "[3B]": "0",
        "HR": "0",
        "RBI": "1",
        "SB": "0",
        "CS": "0",
        "BB": "1",
        "SO": "7",
        "BA": ".100",
        "OBP": ".250",
        "SLG": ".100",
        "OPS": ".350",
        "[OPS+]": "3",
        "rOBA": ".191",
        "[Rbat+]": "6",
        "TB": "1",
        "GIDP": "1",
        "HBP": "1",
        "SH": "0",
        "SF": "0",
        "IBB": "0"
    },
    {
        "Team": "TOR",
		"Player": "Ali Sánchez",
        "Age": "28",
        "Pos": "UT",
        "WAR": "-0.2",
        "G": "5",
        "PA": "11",
        "AB": "11",
        "R": "0",
        "H": "2",
        "[2B]": "1",
        "[3B]": "0",
        "HR": "0",
        "RBI": "0",
        "SB": "0",
        "CS": "0",
        "BB": "0",
        "SO": "3",
        "BA": ".182",
        "OBP": ".182",
        "SLG": ".273",
        "OPS": ".455",
        "[OPS+]": "24",
        "rOBA": ".185",
        "[Rbat+]": "2",
        "TB": "3",
        "GIDP": "1",
        "HBP": "0",
        "SH": "0",
        "SF": "0",
        "IBB": "0"
    },
    {
        "Team": "TOR",
		"Player": "Nick Sandlin",
        "Age": "28",
        "Pos": "P",
        "WAR": "0.0",
        "G": "1",
        "PA": "0",
        "AB": "0",
        "R": "0",
        "H": "0",
        "[2B]": "0",
        "[3B]": "0",
        "HR": "0",
        "RBI": "0",
        "SB": "0",
        "CS": "0",
        "BB": "0",
        "SO": "0",
        "BA": "",
        "OBP": "",
        "SLG": "",
        "OPS": "",
        "[OPS+]": "",
        "rOBA": "",
        "[Rbat+]": "",
        "TB": "0",
        "GIDP": "0",
        "HBP": "0",
        "SH": "0",
        "SF": "0",
        "IBB": "0"
    },
    {
        "Team": "TOR",
		"Player": "Yimi García",
        "Age": "34",
        "Pos": "P",
        "WAR": "0.0",
        "G": "1",
        "PA": "0",
        "AB": "0",
        "R": "0",
        "H": "0",
        "[2B]": "0",
        "[3B]": "0",
        "HR": "0",
        "RBI": "0",
        "SB": "0",
        "CS": "0",
        "BB": "0",
        "SO": "0",
        "BA": "",
        "OBP": "",
        "SLG": "",
        "OPS": "",
        "[OPS+]": "",
        "rOBA": "",
        "[Rbat+]": "",
        "TB": "0",
        "GIDP": "0",
        "HBP": "0",
        "SH": "0",
        "SF": "0",
        "IBB": "0"
    },
    {
        "Team": "TOR",
		"Player": "Jeff Hoffman",
        "Age": "32",
        "Pos": "P",
        "WAR": "0.0",
        "G": "2",
        "PA": "0",
        "AB": "0",
        "R": "0",
        "H": "0",
        "[2B]": "0",
        "[3B]": "0",
        "HR": "0",
        "RBI": "0",
        "SB": "0",
        "CS": "0",
        "BB": "0",
        "SO": "0",
        "BA": "",
        "OBP": "",
        "SLG": "",
        "OPS": "",
        "[OPS+]": "",
        "rOBA": "",
        "[Rbat+]": "",
        "TB": "0",
        "GIDP": "0",
        "HBP": "0",
        "SH": "0",
        "SF": "0",
        "IBB": "0"
    }
]